{
  "project_info": {
    "project_number": "933895412647",
    "project_id": "ismsapplication",
    "storage_bucket": "ismsapplication.firebasestorage.app"
  },
  "client": [
    {
      "client_info": {
        "mobilesdk_app_id": "1:933895412647:android:e92e3012ac280116cf3482",
        "android_client_info": {
          "package_name": "com.isms.wallet"
        }
      },
      "oauth_client": [],
      "api_key": [
        {
          "current_key": "AIzaSyCWxuopHTZdMBO2GA71kxs7HqbPcHys9cQ"
        }
      ],
      "services": {
        "appinvite_service": {
          "other_platform_oauth_client": []
        }
      }
    }
  ],
  "configuration_version": "1"
}